{
  "15599": {
    "name": "SUPER PICSOU GÉANT HS BD DYNASTIE DE PICSOU REV",
    "numero": "2H",
    "date_entree": "10/04/2026",
    "detected_at": "2026-05-04T21:40:11.310257"
  },
  "15681": {
    "name": "PICSOU MAGAZINE HS COLLECTION DELUXE",
    "numero": "3H",
    "date_entree": "08/04/2026",
    "detected_at": "2026-05-04T21:40:11.493743"
  },
  "13159": {
    "name": "Picsou Magazine",
    "numero": "593",
    "date_entree": "19/03/2026",
    "detected_at": "2026-05-04T21:40:11.662357"
  },
  "14068": {
    "name": "Les Trésors de Picsou",
    "numero": "74H",
    "date_entree": "14/03/2026",
    "detected_at": "2026-05-04T21:40:12.031871"
  },
  "14016": {
    "name": "Super Picsou Géant",
    "numero": "253",
    "date_entree": "11/03/2026",
    "detected_at": "2026-05-04T21:40:12.218079"
  },
  "12825": {
    "name": "SUPER PICSOU GÉANT HS SUPER DONALD GÉANT",
    "numero": "6H",
    "date_entree": "18/12/2025",
    "detected_at": "2026-05-04T21:40:12.462753"
  },
  "18268": {
    "name": "SUPER PICSOU GÉANT HS SPÉCIAL DONALD DOUBLE DUCK REV",
    "numero": "6H",
    "date_entree": "06/12/2025",
    "detected_at": "2026-05-04T21:40:12.714436"
  },
  "13459": {
    "name": "SUPER PICSOU GÉANT HS JEUX",
    "numero": "7H",
    "date_entree": "22/11/2025",
    "detected_at": "2026-05-04T21:40:13.024217"
  },
  "15930": {
    "name": "PICSOU MAGAZINE HS COLLECTION DELUXE",
    "numero": "2H",
    "date_entree": "12/11/2025",
    "detected_at": "2026-05-04T21:40:13.152043"
  },
  "17575": {
    "name": "PICSOU ANNIVERSAIRE EN OR REV",
    "numero": "1H",
    "date_entree": "31/10/2025",
    "detected_at": "2026-05-04T21:40:13.332868"
  },
  "12651": {
    "name": "SUPER PICSOU GÉANT HS BD DYNASTIE DE PICSOU",
    "numero": "6H",
    "date_entree": "08/10/2025",
    "detected_at": "2026-05-04T21:40:13.731597"
  },
  "14108": {
    "name": "Journal de Mickey HS",
    "numero": "12H",
    "date_entree": "14/03/2026",
    "detected_at": "2026-05-04T21:40:14.184461"
  },
  "14513": {
    "name": "MICKEY JUNIOR HS JEUX",
    "numero": "13H",
    "date_entree": "04/02/2026",
    "detected_at": "2026-05-04T21:40:16.041662"
  },
  "15190": {
    "name": "Les Chroniques de Fantomiald",
    "numero": "37",
    "date_entree": "11/02/2026",
    "detected_at": "2026-05-04T21:40:16.282048"
  },
  "18262": {
    "name": "SUPER DONALD GÉANT HS REV",
    "numero": "3H",
    "date_entree": "05/02/2025",
    "detected_at": "2026-05-04T21:40:16.631326"
  }
}